es_ingester/__init__.py
es_ingester/core.py
es_ingester-0.1.1.dist-info/METADATA
es_ingester-0.1.1.dist-info/WHEEL
es_ingester-0.1.1.dist-info/entry_points.txt
es_ingester-0.1.1.dist-info/top_level.txt
es_ingester-0.1.1.dist-info/RECORD
