Metadata-Version: 2.1
Name: es-ingester
Version: 0.1.1
Summary: A module for ingesting data into Elasticsearch
Home-page: https://github.com/profmoriarity/es-ingester
Author: Siva Krishna
Author-email: krishna.krish759213@gmail.com
Classifier: Programming Language :: Python :: 3
Classifier: License :: OSI Approved :: MIT License
Classifier: Operating System :: OS Independent
Requires-Python: >=3.6
Requires-Dist: elasticsearch >=7.0.0
Requires-Dist: jsonlines
Requires-Dist: pyyaml
